Metadata-Version: 1.0
Name: Flask-Autodoc
Version: 0.1
Summary: Documentation generator for flask
Home-page: http://github.com/acoomans/flask-autodoc
Author: Arnaud Coomans
Author-email: arnaud.coomans@gmail.com
License: MIT
Platform: any
Classifier: Environment :: Web Environment
Classifier: Intended Audience :: Developers
Classifier: License :: OSI Approved :: MIT License
Classifier: Operating System :: OS Independent
Classifier: Programming Language :: Python
Classifier: Topic :: Internet :: WWW/HTTP :: Dynamic Content
Classifier: Topic :: Software Development :: Libraries :: Python Modules
